ansys/grpc/dpf/__init__.py
ansys/grpc/dpf/_version.py
ansys/grpc/dpf/available_result_pb2.py
ansys/grpc/dpf/available_result_pb2_grpc.py
ansys/grpc/dpf/base_pb2.py
ansys/grpc/dpf/base_pb2_grpc.py
ansys/grpc/dpf/collection_pb2.py
ansys/grpc/dpf/collection_pb2_grpc.py
ansys/grpc/dpf/cyclic_support_pb2.py
ansys/grpc/dpf/cyclic_support_pb2_grpc.py
ansys/grpc/dpf/data_sources_pb2.py
ansys/grpc/dpf/data_sources_pb2_grpc.py
ansys/grpc/dpf/data_tree_pb2.py
ansys/grpc/dpf/data_tree_pb2_grpc.py
ansys/grpc/dpf/dpf_any_message_pb2.py
ansys/grpc/dpf/dpf_any_message_pb2_grpc.py
ansys/grpc/dpf/dpf_any_pb2.py
ansys/grpc/dpf/dpf_any_pb2_grpc.py
ansys/grpc/dpf/field_definition_pb2.py
ansys/grpc/dpf/field_definition_pb2_grpc.py
ansys/grpc/dpf/field_pb2.py
ansys/grpc/dpf/field_pb2_grpc.py
ansys/grpc/dpf/generic_data_container_pb2.py
ansys/grpc/dpf/generic_data_container_pb2_grpc.py
ansys/grpc/dpf/generic_support_pb2.py
ansys/grpc/dpf/generic_support_pb2_grpc.py
ansys/grpc/dpf/label_space_pb2.py
ansys/grpc/dpf/label_space_pb2_grpc.py
ansys/grpc/dpf/meshed_region_pb2.py
ansys/grpc/dpf/meshed_region_pb2_grpc.py
ansys/grpc/dpf/operator_config_pb2.py
ansys/grpc/dpf/operator_config_pb2_grpc.py
ansys/grpc/dpf/operator_pb2.py
ansys/grpc/dpf/operator_pb2_grpc.py
ansys/grpc/dpf/result_info_pb2.py
ansys/grpc/dpf/result_info_pb2_grpc.py
ansys/grpc/dpf/scoping_pb2.py
ansys/grpc/dpf/scoping_pb2_grpc.py
ansys/grpc/dpf/session_pb2.py
ansys/grpc/dpf/session_pb2_grpc.py
ansys/grpc/dpf/support_pb2.py
ansys/grpc/dpf/support_pb2_grpc.py
ansys/grpc/dpf/support_service_pb2.py
ansys/grpc/dpf/support_service_pb2_grpc.py
ansys/grpc/dpf/time_freq_support_pb2.py
ansys/grpc/dpf/time_freq_support_pb2_grpc.py
ansys/grpc/dpf/workflow_message_pb2.py
ansys/grpc/dpf/workflow_message_pb2_grpc.py
ansys/grpc/dpf/workflow_pb2.py
ansys/grpc/dpf/workflow_pb2_grpc.py
ansys_grpc_dpf-0.8.1.dist-info/LICENSE
ansys_grpc_dpf-0.8.1.dist-info/METADATA
ansys_grpc_dpf-0.8.1.dist-info/WHEEL
ansys_grpc_dpf-0.8.1.dist-info/top_level.txt
ansys_grpc_dpf-0.8.1.dist-info/RECORD
