Metadata-Version: 2.1
Name: ansys-grpc-dpf
Version: 0.8.1
Summary: Package for ansys-grpc-dpf python gRPC client
Author: ANSYS
Author-email: ramdane.lagha@ansys.com
Maintainer-email: pyansys.maintainers@ansys.com
License: Ansys Redistribution License
Classifier: Development Status :: 4 - Beta
Classifier: Intended Audience :: Science/Research
Classifier: Topic :: Scientific/Engineering :: Information Analysis
Classifier: Operating System :: Microsoft :: Windows
Classifier: Operating System :: POSIX
Classifier: Programming Language :: Python :: 3.7
Classifier: Programming Language :: Python :: 3.8
Classifier: Programming Language :: Python :: 3.9
Classifier: Programming Language :: Python :: 3.10
Requires-Python: >=3.7
License-File: LICENSE
Requires-Dist: grpcio
Requires-Dist: google-api-python-client
